README.md
setup.cfg
setup.py
cryptofinder/__init__.py
cryptofinder/cli.py
cryptofinder/config.py
cryptofinder/controller.py
cryptofinder/logger.py
cryptofinder/models.py
cryptofinder/ticker.py
cryptofinder/util.py
cryptofinder/views.py
cryptofinder.egg-info/PKG-INFO
cryptofinder.egg-info/SOURCES.txt
cryptofinder.egg-info/dependency_links.txt
cryptofinder.egg-info/entry_points.txt
cryptofinder.egg-info/requires.txt
cryptofinder.egg-info/top_level.txt