Metadata-Version: 1.1
Name: cryptofinder
Version: 0.1.7
Summary: Command-line program for finding cryptocurrencies
Home-page: https://github.com/jorrinpollard/cryptofinder
Author: Jorrin Pollard
Author-email: me@jorrinpollard.com
License: MIT
Keywords: bitcoin,coinmarketcap,crypto,cryptocurrencies,cryptocurrency,finance,financial,investment
Platform: UNKNOWN
Classifier: Development Status :: 3 - Alpha
Classifier: Environment :: Console
Classifier: Intended Audience :: End Users/Desktop
Classifier: License :: OSI Approved :: MIT License
Classifier: Natural Language :: English
Classifier: Operating System :: OS Independent
Classifier: Programming Language :: Python :: 3
Classifier: Topic :: Office/Business :: Financial :: Investment
